{
 "Resources": {
  "yoadtamar1234566EF2404B": {
   "Type": "AWS::S3::Bucket",
   "UpdateReplacePolicy": "Retain",
   "DeletionPolicy": "Retain",
   "Metadata": {
    "aws:cdk:path": "LinkupCdkStack/yoad-tamar-123456/Resource"
   }
  },
  "CDKMetadata": {
   "Type": "AWS::CDK::Metadata",
   "Properties": {
    "Analytics": "v2:deflate64:H4sIAAAAAAAA/zPSMzQx0zNQTCwv1k1OydbNyUzSqw4uSUzO1glKLc4vLUpO1UksL44vNtardipNzk4t0XFOy4OwakFM/9KSglKwIEx9rU5efkqqXlaxfpmRgZ6hqZ6hYlZxZqZuUWleSWZuql4QhAYAZ+Nas3oAAAA="
   },
   "Metadata": {
    "aws:cdk:path": "LinkupCdkStack/CDKMetadata/Default"
   }
  }
 },
 "Outputs": {
  "yoadtamar123456Output": {
   "Value": {
    "Ref": "yoadtamar1234566EF2404B"
   }
  }
 },
 "Parameters": {
  "BootstrapVersion": {
   "Type": "AWS::SSM::Parameter::Value<String>",
   "Default": "/cdk-bootstrap/hnb659fds/version",
   "Description": "Version of the CDK Bootstrap resources in this environment, automatically retrieved from SSM Parameter Store. [cdk:skip]"
  }
 },
 "Rules": {
  "CheckBootstrapVersion": {
   "Assertions": [
    {
     "Assert": {
      "Fn::Not": [
       {
        "Fn::Contains": [
         [
          "1",
          "2",
          "3",
          "4",
          "5"
         ],
         {
          "Ref": "BootstrapVersion"
         }
        ]
       }
      ]
     },
     "AssertDescription": "CDK bootstrap stack version 6 required. Please run 'cdk bootstrap' with a recent version of the CDK CLI."
    }
   ]
  }
 }
}